pulumi_tailscale/__init__.py
pulumi_tailscale/_inputs.py
pulumi_tailscale/_utilities.py
pulumi_tailscale/acl.py
pulumi_tailscale/aws_external_id.py
pulumi_tailscale/contacts.py
pulumi_tailscale/device_authorization.py
pulumi_tailscale/device_key.py
pulumi_tailscale/device_subnet_routes.py
pulumi_tailscale/device_tags.py
pulumi_tailscale/dns_configuration.py
pulumi_tailscale/dns_nameservers.py
pulumi_tailscale/dns_preferences.py
pulumi_tailscale/dns_search_paths.py
pulumi_tailscale/dns_split_nameservers.py
pulumi_tailscale/federated_identity.py
pulumi_tailscale/get4_via6.py
pulumi_tailscale/get_acl.py
pulumi_tailscale/get_device.py
pulumi_tailscale/get_devices.py
pulumi_tailscale/get_user.py
pulumi_tailscale/get_users.py
pulumi_tailscale/logstream_configuration.py
pulumi_tailscale/oauth_client.py
pulumi_tailscale/outputs.py
pulumi_tailscale/posture_integration.py
pulumi_tailscale/provider.py
pulumi_tailscale/pulumi-plugin.json
pulumi_tailscale/py.typed
pulumi_tailscale/tailnet_key.py
pulumi_tailscale/tailnet_settings.py
pulumi_tailscale/webhook.py
pulumi_tailscale/config/__init__.py
pulumi_tailscale/config/__init__.pyi
pulumi_tailscale/config/vars.py
pulumi_tailscale-0.24.0.dist-info/METADATA
pulumi_tailscale-0.24.0.dist-info/WHEEL
pulumi_tailscale-0.24.0.dist-info/top_level.txt
pulumi_tailscale-0.24.0.dist-info/RECORD
